schemed_yaml_config/__about__.py
schemed_yaml_config/__init__.py
schemed_yaml_config/__main__.py
schemed_yaml_config/schemed_yaml_config.py
schemed_yaml_config-1.0.5.dist-info/LICENSE
schemed_yaml_config-1.0.5.dist-info/METADATA
schemed_yaml_config-1.0.5.dist-info/WHEEL
schemed_yaml_config-1.0.5.dist-info/entry_points.txt
schemed_yaml_config-1.0.5.dist-info/top_level.txt
schemed_yaml_config-1.0.5.dist-info/RECORD
