Metadata-Version: 2.1
Name: schemed-yaml-config
Version: 1.0.5
Summary: UNKNOWN
Home-page: https://github.com/lamehost/schemed-yaml-config/
Author: Marco Marzetti
Author-email: marco@lamehost.it
License: UNKNOWN
Platform: UNKNOWN
Requires-Dist: PyYAML (==6.0)
Requires-Dist: jsonschema (==4.1.0)
Requires-Dist: toml (==0.10.2)
Requires-Dist: yamlordereddictloader (==0.4.0)
